xautic/__init__.py
xautic/_version.py
xautic/main.py
xautic/utils.py
xautic-1.0.1.dist-info/LICENSE
xautic-1.0.1.dist-info/METADATA
xautic-1.0.1.dist-info/WHEEL
xautic-1.0.1.dist-info/top_level.txt
xautic-1.0.1.dist-info/RECORD
